cmakemake/CMakeMake.py
cmakemake/CMakeWriter.py
cmakemake/ConfigurationBuilder.py
cmakemake/ConfigurationDetector.py
cmakemake/FileFilter.py
cmakemake/PublicPredictor.py
cmakemake/__init__.py
cmakemake/concepts.py
cmakemake/constants.py
cmakemake/keywords.py
cmakemake/utils.py
cmakemake_cli/__init__.py
cmakemake_cli/main.py
cmakemake-0.0.2.dist-info/LICENSE
cmakemake-0.0.2.dist-info/METADATA
cmakemake-0.0.2.dist-info/WHEEL
cmakemake-0.0.2.dist-info/entry_points.txt
cmakemake-0.0.2.dist-info/top_level.txt
cmakemake-0.0.2.dist-info/RECORD
