Metadata-Version: 2.1
Name: cmakemake
Version: 0.0.2
Summary: Make CMake files
Home-page: https://gitee.com/zhuuuoyue/cmakemake
Author: zhuoy
Author-email: zhuoyue_cn@yeah.net
License: MIT
License-File: LICENSE
